xontrib/cmd_done.py
xontrib/notifypy/__init__.py
xontrib/notifypy/example_notification_sound.wav
xontrib/notifypy/exceptions.py
xontrib/notifypy/notify.py
xontrib/notifypy/os_notifiers/__init__.py
xontrib/notifypy/os_notifiers/_base.py
xontrib/notifypy/os_notifiers/binaries/Notificator.app/Contents/Info.plist
xontrib/notifypy/os_notifiers/binaries/Notificator.app/Contents/MacOS/applet
xontrib/notifypy/os_notifiers/binaries/Notificator.app/Contents/PkgInfo
xontrib/notifypy/os_notifiers/binaries/Notificator.app/Contents/Resources/Scripts/main.scpt
xontrib/notifypy/os_notifiers/binaries/Notificator.app/Contents/Resources/Scripts/notificator
xontrib/notifypy/os_notifiers/binaries/Notificator.app/Contents/Resources/applet.icns
xontrib/notifypy/os_notifiers/binaries/Notificator.app/Contents/Resources/applet.rsrc
xontrib/notifypy/os_notifiers/linux.py
xontrib/notifypy/os_notifiers/macos.py
xontrib/notifypy/os_notifiers/windows.py
xontrib/notifypy/py-logo.png
xontrib_cmd_done-0.2.2.dist-info/LICENSE
xontrib_cmd_done-0.2.2.dist-info/WHEEL
xontrib_cmd_done-0.2.2.dist-info/METADATA
xontrib_cmd_done-0.2.2.dist-info/RECORD
