Metadata-Version: 2.1
Name: xontrib-cmd-done
Version: 0.2.2
Summary: Send notification once long running command is finished. Add duration PROMP_FIELD.
Home-page: https://github.com/jnoortheen/xontrib-cmd-done
License: MIT
Keywords: xontrib,xonsh
Author: Noortheen Raja J
Author-email: jnoortheen@gmail.com
Requires-Python: >=3.6
Classifier: Intended Audience :: Developers
Classifier: License :: OSI Approved :: MIT License
Classifier: Natural Language :: English
Classifier: Operating System :: OS Independent
Classifier: Programming Language :: Python
Classifier: Programming Language :: Python :: 3
Classifier: Programming Language :: Python :: 3.6
Classifier: Programming Language :: Python :: 3.7
Classifier: Programming Language :: Python :: 3.8
Classifier: Programming Language :: Python :: 3.9
Classifier: Topic :: System :: Shells
Classifier: Topic :: System :: System Shells
Classifier: Topic :: Terminals
Requires-Dist: xonsh (>=0.9.20)
Project-URL: Code, https://github.com/jnoortheen/xontrib-cmd-done
Project-URL: Documentation, https://github.com/jnoortheen/xontrib-cmd-done/blob/master/README.md
Project-URL: Issue tracker, https://github.com/jnoortheen/xontrib-cmd-done/issues
Project-URL: Repository, https://github.com/jnoortheen/xontrib-cmd-done
